{
  "response_code": 0,
  "results": [
    {
      "category": "Geography",
      "type": "multiple",
      "difficulty": "hard",
      "question": "In which city, is the Big Nickel located in Canada?",
      "correct_answer": "Sudbury",
      "incorrect_answers": [
        "Calgary, Alberta",
        "Halifax, Nova Scotia ",
        "Victoria, British Columbia"
      ]
    },
    {
      "category": "Sports",
      "type": "multiple",
      "difficulty": "medium",
      "question": "Which German sportswear company&#039;s logo is the &#039;Formstripe&#039;?",
      "correct_answer": "Puma",
      "incorrect_answers": [
        "Nike",
        "Adidas",
        "Reebok"
      ]
    },
    {
      "category": "Science: Computers",
      "type": "multiple",
      "difficulty": "medium",
      "question": "When was the programming language &quot;C#&quot; released?",
      "correct_answer": "2000",
      "incorrect_answers": [
        "1998",
        "1999",
        "2001"
      ]
    },
    {
      "category": "Entertainment: Film",
      "type": "multiple",
      "difficulty": "easy",
      "question": "What was the title of the first Bond movie, released in 1962?",
      "correct_answer": "Dr. No",
      "incorrect_answers": [
        "From Russia with Love",
        "Goldfinger",
        "Thunderball"
      ]
    },
    {
      "category": "Politics",
      "type": "multiple",
      "difficulty": "medium",
      "question": "Before 2011, &quot;True Capitalist Radio&quot; was known by a different name. What was that name?",
      "correct_answer": "True Conservative Radio",
      "incorrect_answers": [
        "True Republican Radio",
        "Texan Capitalist Radio",
        "United Capitalists"
      ]
    },
    {
      "category": "Geography",
      "type": "multiple",
      "difficulty": "medium",
      "question": "What are the four corner states of the US?",
      "correct_answer": "Utah, Colorado, Arizona, New Mexico",
      "incorrect_answers": [
        "Oregon, Idaho, Nevada, Utah",
        "Kansas, Oklahoma, Arkansas, Louisiana",
        "South Dakota, Minnesota, Nebraska, Iowa"
      ]
    },
    {
      "category": "Geography",
      "type": "multiple",
      "difficulty": "hard",
      "question": "Which country is completely landlocked by South Africa?",
      "correct_answer": "Lesotho",
      "incorrect_answers": [
        "Swaziland",
        "Botswana",
        "Zimbabwe"
      ]
    },
    {
      "category": "Entertainment: Film",
      "type": "multiple",
      "difficulty": "medium",
      "question": "In which African country was the 2006 film &#039;Blood Diamond&#039; mostly set in?",
      "correct_answer": "Sierra Leone",
      "incorrect_answers": [
        "Liberia",
        "Burkina Faso",
        "Central African Republic"
      ]
    },
    {
      "category": "Science: Gadgets",
      "type": "multiple",
      "difficulty": "medium",
      "question": "What are the base station trackers used for the HTC Vive called?",
      "correct_answer": "Lighthouse",
      "incorrect_answers": [
        "Motion",
        "Constellation ",
        "Trackers"
      ]
    },
    {
      "category": "Geography",
      "type": "multiple",
      "difficulty": "hard",
      "question": "What is the name of one of the Neo-Aramaic languages spoken by the Jewish population from Northwestern Iraq?",
      "correct_answer": "Lishana Deni",
      "incorrect_answers": [
        "Hulaul&aacute;",
        "Lishan Didan",
        "Chaldean Neo-Aramaic"
      ]
    },
    {
      "category": "Mythology",
      "type": "multiple",
      "difficulty": "easy",
      "question": "This Greek goddess&#039;s name was chosen for the dwarf planet responsible for discord on Pluto&#039;s classification amongst astronomers.",
      "correct_answer": "Eris",
      "incorrect_answers": [
        "Charon",
        "Ceres",
        "Dysnomia"
      ]
    },
    {
      "category": "Science: Computers",
      "type": "multiple",
      "difficulty": "medium",
      "question": "On which day did the World Wide Web go online?",
      "correct_answer": "December 20, 1990",
      "incorrect_answers": [
        "December 17, 1996",
        "November 12, 1990",
        "November 24, 1995"
      ]
    },
    {
      "category": "Entertainment: Music",
      "type": "multiple",
      "difficulty": "easy",
      "question": "What was the name of singer Frank Ocean&#039;s second studio album, which was released on August 20, 2016?",
      "correct_answer": "Blonde",
      "incorrect_answers": [
        "Brunette",
        "Black",
        "Burgundy"
      ]
    },
    {
      "category": "Entertainment: Cartoon & Animations",
      "type": "multiple",
      "difficulty": "easy",
      "question": "Who voices for Ruby in the animated series RWBY?",
      "correct_answer": "Lindsay Jones",
      "incorrect_answers": [
        "Tara Strong",
        "Jessica Nigri",
        "Hayden Panettiere"
      ]
    },
    {
      "category": "General Knowledge",
      "type": "multiple",
      "difficulty": "easy",
      "question": "What is the Spanish word for &quot;donkey&quot;?",
      "correct_answer": "Burro",
      "incorrect_answers": [
        "Caballo",
        "Toro",
        "Perro"
      ]
    },
    {
      "category": "History",
      "type": "multiple",
      "difficulty": "easy",
      "question": "When did the Battle of the Somme begin?",
      "correct_answer": "July 1st, 1916",
      "incorrect_answers": [
        "August 1st, 1916",
        "July 2nd, 1916",
        "June 30th, 1916"
      ]
    },
    {
      "category": "Entertainment: Music",
      "type": "multiple",
      "difficulty": "easy",
      "question": "In Mean Girls, who has breasts that tell when it&#039;s raining?",
      "correct_answer": "Karen Smith",
      "incorrect_answers": [
        "Gretchen Weiners",
        "Janice Ian",
        "Cady Heron"
      ]
    },
    {
      "category": "History",
      "type": "multiple",
      "difficulty": "medium",
      "question": "Against which country did the Dutch Republic fight the Eighty Years&#039; War?",
      "correct_answer": "Spain",
      "incorrect_answers": [
        "France",
        "England",
        "Portugal"
      ]
    },
    {
      "category": "Geography",
      "type": "multiple",
      "difficulty": "medium",
      "question": "Where is the world&#039;s oldest still operational space launch facility located?",
      "correct_answer": "Kazakhstan",
      "incorrect_answers": [
        "Russia",
        "Iran",
        "United States"
      ]
    },
    {
      "category": "General Knowledge",
      "type": "multiple",
      "difficulty": "easy",
      "question": "Which one of these is not a typical European sword design?",
      "correct_answer": "Scimitar",
      "incorrect_answers": [
        "Falchion",
        "Ulfberht",
        "Flamberge"
      ]
    },
    {
      "category": "Entertainment: Music",
      "type": "multiple",
      "difficulty": "medium",
      "question": "Which country does the electronic music duo &quot;The Knife&quot; originate from?",
      "correct_answer": "Sweden",
      "incorrect_answers": [
        "Finland",
        "Denmark",
        "Norway"
      ]
    },
    {
      "category": "Entertainment: Television",
      "type": "multiple",
      "difficulty": "medium",
      "question": "What is the name of the &quot;Flash&quot; and &quot;Arrow&quot; spinoff featuring a team of characters that have appeared on both shows?",
      "correct_answer": "Legends of Tomorrow",
      "incorrect_answers": [
        "Heroes of Tomorrow",
        "The Justice Society of America",
        "The Justice Society"
      ]
    },
    {
      "category": "Science: Computers",
      "type": "multiple",
      "difficulty": "medium",
      "question": "What does the term GPU stand for?",
      "correct_answer": "Graphics Processing Unit",
      "incorrect_answers": [
        "Gaming Processor Unit",
        "Graphite Producing Unit",
        "Graphical Proprietary Unit"
      ]
    },
    {
      "category": "Geography",
      "type": "multiple",
      "difficulty": "easy",
      "question": "What is the capital of Spain?",
      "correct_answer": "Madrid",
      "incorrect_answers": [
        "Barcelona",
        "Sevilla",
        "Toledo"
      ]
    },
    {
      "category": "Entertainment: Film",
      "type": "multiple",
      "difficulty": "easy",
      "question": "The 2016 Disney animated film &#039;Moana&#039; is based on which culture?",
      "correct_answer": "Polynesian",
      "incorrect_answers": [
        "Native American",
        "Japanese",
        "Nordic"
      ]
    },
    {
      "category": "Entertainment: Television",
      "type": "multiple",
      "difficulty": "hard",
      "question": "In &quot;Star Trek&quot;, what sauce is commonly used by Klingons on bregit lung?",
      "correct_answer": "Grapok sauce",
      "incorrect_answers": [
        "Gazorpazorp pudding",
        "Sweet chili sauce",
        "Grapork sauce"
      ]
    },
    {
      "category": "Entertainment: Video Games",
      "type": "multiple",
      "difficulty": "medium",
      "question": "What is the name of the common, gun-toting enemies of the &quot;Oddworld&quot; video game series?",
      "correct_answer": "Sligs",
      "incorrect_answers": [
        "Scrabs",
        "Slogs",
        "Glukkons"
      ]
    },
    {
      "category": "Politics",
      "type": "multiple",
      "difficulty": "medium",
      "question": "What is former United States President Bill Clinton&#039;s full name?",
      "correct_answer": "William Jefferson Clinton",
      "incorrect_answers": [
        "William Roosevelt Clinton",
        "William Truman Clinton",
        "William Lincoln Clinton"
      ]
    },
    {
      "category": "Entertainment: Video Games",
      "type": "multiple",
      "difficulty": "hard",
      "question": "Which of these characters wasn&#039;t a villian in Club Penguin?",
      "correct_answer": "The Director",
      "incorrect_answers": [
        "Herbert P. Bear",
        "Tusk",
        "Ultimate Proto-Bot 10000"
      ]
    },
    {
      "category": "Science & Nature",
      "type": "multiple",
      "difficulty": "medium",
      "question": "The Sun consists of mostly which two elements?",
      "correct_answer": "Hydrogen &amp; Helium",
      "incorrect_answers": [
        "Hydrogen &amp; Nitrogen",
        "Carbon &amp; Nitrogen",
        "Carbon &amp; Helium"
      ]
    },
    {
      "category": "General Knowledge",
      "type": "multiple",
      "difficulty": "hard",
      "question": "If someone said &quot;you are olid&quot;, what would they mean?",
      "correct_answer": "You smell extremely unpleasant.",
      "incorrect_answers": [
        "You are out of shape\/weak.",
        "Your appearance is repulsive.",
        "You are incomprehensible\/an idiot."
      ]
    },
    {
      "category": "Entertainment: Video Games",
      "type": "multiple",
      "difficulty": "hard",
      "question": "In the Kingdom Hearts series, which is not an optional boss you can fight?",
      "correct_answer": "Master Yen Sid",
      "incorrect_answers": [
        "Sephiroth",
        "Julius",
        "Kurt Zisa"
      ]
    },
    {
      "category": "Entertainment: Books",
      "type": "multiple",
      "difficulty": "hard",
      "question": "Which fictional English county was the setting for Thomas Hardy&#039;s novels?",
      "correct_answer": "Wessex",
      "incorrect_answers": [
        "Barsetshire",
        "Fulchester",
        "Ambridge"
      ]
    },
    {
      "category": "Science & Nature",
      "type": "multiple",
      "difficulty": "hard",
      "question": "Autosomal-dominant Compelling Helio-Ophthalmic Outburst syndrome is the need to do what when seeing the Sun?",
      "correct_answer": "Sneeze",
      "incorrect_answers": [
        "Cough",
        "Yawn",
        "Hiccup"
      ]
    },
    {
      "category": "Entertainment: Video Games",
      "type": "multiple",
      "difficulty": "hard",
      "question": "In Disney&#039;s &quot;Toontown Online&quot;, which of these species wasn&#039;t available as a Toon?",
      "correct_answer": "Cow",
      "incorrect_answers": [
        "Monkey",
        "Bear",
        "Pig"
      ]
    },
    {
      "category": "Entertainment: Video Games",
      "type": "multiple",
      "difficulty": "easy",
      "question": "In Fallout: New Vegas, which one of these casinos can you not play in?",
      "correct_answer": "Lucky 38",
      "incorrect_answers": [
        "The Tops",
        "Gammorah",
        "Ultra-Luxe"
      ]
    },
    {
      "category": "Mythology",
      "type": "multiple",
      "difficulty": "hard",
      "question": "Which Norse God has a horse named Sleipnir?",
      "correct_answer": "Odin",
      "incorrect_answers": [
        "Thor",
        "Frigg",
        "Balder"
      ]
    },
    {
      "category": "Art",
      "type": "multiple",
      "difficulty": "hard",
      "question": "The painting &quot;The Starry Night&quot; by Vincent van Gogh was part of which art movement?",
      "correct_answer": "Post-Impressionism",
      "incorrect_answers": [
        "Romanticism",
        "Neoclassical",
        "Impressionism"
      ]
    },
    {
      "category": "Entertainment: Musicals & Theatres",
      "type": "multiple",
      "difficulty": "medium",
      "question": "The World Chess Championship in Chess, Act 1 is set in which Italian city?",
      "correct_answer": "Merano",
      "incorrect_answers": [
        "Venice",
        "Milan",
        "Rome"
      ]
    },
    {
      "category": "History",
      "type": "multiple",
      "difficulty": "easy",
      "question": "Abolitionist John Brown raided the arsenal in which Virginia Town?",
      "correct_answer": "Harper&#039;s Ferry",
      "incorrect_answers": [
        "Richmond",
        "Harrisonburg",
        "Martinsburg"
      ]
    },
    {
      "category": "Entertainment: Video Games",
      "type": "multiple",
      "difficulty": "medium",
      "question": "Who is the half-demon character in Divinity: Original Sin 2 who you talk to to transition between acts?",
      "correct_answer": "Malady",
      "incorrect_answers": [
        "Meister Siva",
        "Gawin",
        "Exter"
      ]
    },
    {
      "category": "Entertainment: Video Games",
      "type": "multiple",
      "difficulty": "medium",
      "question": "Who was Tetris created by?",
      "correct_answer": "Alexey Pajitnov",
      "incorrect_answers": [
        "Toru Iwatani",
        "Allan Alcorn",
        "William Higinbotham"
      ]
    },
    {
      "category": "Geography",
      "type": "multiple",
      "difficulty": "easy",
      "question": "Greenland is a part of which kingdom?",
      "correct_answer": "Denmark",
      "incorrect_answers": [
        "Sweden",
        "Norway",
        "United Kingdom"
      ]
    }
  ]
}
